geotechdata/__init__.py
geotechdata/borehole.py
geotechdata/groundwater.py
geotechdata/labtest.py
geotechdata/type.py
geotechdata-0.1.1.dist-info/licenses/LICENSE
test/__init__.py
test/test_spt.py
geotechdata-0.1.1.dist-info/METADATA
geotechdata-0.1.1.dist-info/WHEEL
geotechdata-0.1.1.dist-info/top_level.txt
geotechdata-0.1.1.dist-info/RECORD
