Metadata-Version: 2.4
Name: geotechdata
Version: 0.1.1
Summary: A general Geotechnical data structure and utilities for Python
Home-page: https://github.com/geocodes-eng/geotechdata
Author: geocoder-eng
Keywords: geotechnical,borehole,spt,groundwater
Classifier: Programming Language :: Python :: 3
Classifier: License :: OSI Approved :: MIT License
Classifier: Operating System :: OS Independent
Requires-Python: >=3.7
License-File: LICENSE
Requires-Dist: pandas
Requires-Dist: matplotlib
Dynamic: license-file
